Fleepy-0.2.1.dist-info/DESCRIPTION.rst
Fleepy-0.2.1.dist-info/METADATA
Fleepy-0.2.1.dist-info/RECORD
Fleepy-0.2.1.dist-info/WHEEL
Fleepy-0.2.1.dist-info/metadata.json
Fleepy-0.2.1.dist-info/top_level.txt
fleepy/__init__.py
fleepy/_account.py
fleepy/_alias.py
fleepy/_avatar.py
fleepy/_contact.py
fleepy/_conversation.py
fleepy/_file.py
fleepy/_info.py
fleepy/_message.py
fleepy/_search.py
fleepy/_server.py
fleepy/_task.py
fleepy/fleepy.py
